{
	"name": "Bunge Jungle",
	"short_name": "Bunge Jungle",
	"description": "Bored of all the games you played? Are you tired of tapping with your fingers? Then stop playing these orthodox games. Bunge Jungle is here for you to keep you off from the stress of tapping because the only job for you is to tilt your device! Crazy game mechanics are here for you to try! You are jumping! Not by tapping with your fingers! The only task for you is to tilt your device the way you want to jump. Avoid the barricades because if you jump on them, it’s game over for you, sadly! Jump along, and gain some points!  So what are you waiting for now? Let yourself loose because the time has come for you to download the best jumping game there is now on the market! ",
	"start_url": "index.html",
	"display": "fullscreen",
	"orientation": "portrait",
	"background_color": "#000000",
	"icons": [
		{
			"src": "icons/icon-16.png",
			"sizes": "16x16",
			"type": "image/png"
		},
		{
			"src": "icons/icon-32.png",
			"sizes": "32x32",
			"type": "image/png"
		},
		{
			"src": "icons/icon-114.png",
			"sizes": "114x114",
			"type": "image/png"
		},
		{
			"src": "icons/icon-128.png",
			"sizes": "128x128",
			"type": "image/png"
		},
		{
			"src": "icons/icon-256.png",
			"sizes": "256x256",
			"type": "image/png"
		}
	]
}